{
  "project_info": {
    "project_number": "1000756317145",
    "firebase_url": "https://jongseolproject-default-rtdb.firebaseio.com",
    "project_id": "jongseolproject",
    "storage_bucket": "jongseolproject.appspot.com"
  },
  "client": [
    {
      "client_info": {
        "mobilesdk_app_id": "1:1000756317145:android:d8ac2782ee4cfb5aeba7c8",
        "android_client_info": {
          "package_name": "com.example.project"
        }
      },
      "oauth_client": [
        {
          "client_id": "1000756317145-sfkg4d0te0419jd5pbfdcmudbiu89clf.apps.googleusercontent.com",
          "client_type": 3
        }
      ],
      "api_key": [
        {
          "current_key": "AIzaSyA4j8BMtpkHZDpfX49iC69-f2JSAO8r0Hc"
        }
      ],
      "services": {
        "appinvite_service": {
          "other_platform_oauth_client": [
            {
              "client_id": "1000756317145-sfkg4d0te0419jd5pbfdcmudbiu89clf.apps.googleusercontent.com",
              "client_type": 3
            }
          ]
        }
      }
    }
  ],
  "configuration_version": "1"
}